caas_jupyter_tools/__init__.py
caas_jupyter_tools-0.0.2.dist-info/METADATA
caas_jupyter_tools-0.0.2.dist-info/WHEEL
caas_jupyter_tools-0.0.2.dist-info/top_level.txt
caas_jupyter_tools-0.0.2.dist-info/RECORD
