Metadata-Version: 2.1
Name: caas_jupyter_tools
Version: 0.0.2
Summary: caas_jupyter_tools
Requires-Python: >=3.6
